dmri_amico-2.1.1.dist-info/RECORD
dmri_amico-2.1.1.dist-info/WHEEL
dmri_amico-2.1.1.dist-info/top_level.txt
dmri_amico-2.1.1.dist-info/METADATA
dmri_amico-2.1.1.dist-info/licenses/LICENSE
amico/util.py
amico/lut.cpython-312-darwin.so
amico/__init__.py
amico/core.py
amico/models.cpython-312-darwin.so
amico/preproc.py
amico/scheme.py
amico/synthesis.py
amico/directions/ndirs=8000.bin
amico/directions/ndirs=4000.bin
amico/directions/ndirs=10000.bin
amico/directions/htable_ndirs=4500.bin
amico/directions/htable_ndirs=8500.bin
amico/directions/htable_ndirs=2000.bin
amico/directions/htable_ndirs=6500.bin
amico/directions/ndirs=500.bin
amico/directions/ndirs=2500.bin
amico/directions/ndirs=6000.bin
amico/directions/htable_ndirs=6000.bin
amico/directions/htable_ndirs=2500.bin
amico/directions/ndirs=6500.bin
amico/directions/ndirs=2000.bin
amico/directions/ndirs=4500.bin
amico/directions/ndirs=8500.bin
amico/directions/htable_ndirs=8000.bin
amico/directions/ndirs=32761.bin
amico/directions/htable_ndirs=4000.bin
amico/directions/htable_ndirs=1000.bin
amico/directions/htable_ndirs=5500.bin
amico/directions/htable_ndirs=9500.bin
amico/directions/ndirs=9000.bin
amico/directions/htable_ndirs=1.bin
amico/directions/ndirs=1500.bin
amico/directions/ndirs=5000.bin
amico/directions/htable_ndirs=32761.bin
amico/directions/ndirs=3500.bin
amico/directions/ndirs=7000.bin
amico/directions/htable_ndirs=500.bin
amico/directions/htable_ndirs=3000.bin
amico/directions/htable_ndirs=7500.bin
amico/directions/ndirs=7500.bin
amico/directions/ndirs=3000.bin
amico/directions/htable_ndirs=7000.bin
amico/directions/htable_ndirs=3500.bin
amico/directions/htable_ndirs=10000.bin
amico/directions/htable_ndirs=9000.bin
amico/directions/htable_ndirs=5000.bin
amico/directions/htable_ndirs=1500.bin
amico/directions/ndirs=5500.bin
amico/directions/ndirs=1000.bin
amico/directions/ndirs=9500.bin
amico/directions/ndirs=1.bin
amico/.dylibs/libopenblas.0.dylib
