Metadata-Version: 2.4
Name: dmri-amico
Version: 2.1.1
Summary: Accelerated Microstructure Imaging via Convex Optimization (AMICO)
Home-page: https://github.com/daducci/AMICO
Download-URL: https://pypi.org/project/dmri-amico
Author: Alessandro Daducci
Author-email: alessandro.daducci@univr.it
Maintainer: Alessandro Daducci
Maintainer-email: alessandro.daducci@univr.it
License: Proprietary License
Project-URL: Homepage, https://github.com/daducci/AMICO
Project-URL: Documentation, https://github.com/daducci/AMICO/wiki
Project-URL: Source, https://github.com/daducci/AMICO
Project-URL: Changelog, https://github.com/daducci/AMICO/blob/master/CHANGELOG.md
Project-URL: Download, https://pypi.org/project/dmri-amico
Project-URL: Tracker, https://github.com/daducci/AMICO/issues
Keywords: Neuroimaging,Diffusion MRI,Microstructure Imaging
Classifier: Topic :: Scientific/Engineering :: Image Processing
Classifier: License :: Other/Proprietary License
Classifier: Programming Language :: Cython
Classifier: Programming Language :: Python
Classifier: Operating System :: OS Independent
Classifier: Intended Audience :: Science/Research
Requires-Python: >=3.6
License-File: LICENSE
Requires-Dist: numpy>=1.19.5
Requires-Dist: scipy>=1.5.4
Requires-Dist: dipy>=1.4.1
Requires-Dist: threadpoolctl>=3.1.0
Requires-Dist: dmri-dicelib>=1.0.3
Requires-Dist: importlib-metadata>=4.8.3; python_version < "3.8"
Dynamic: download-url
Dynamic: license-file
